recipe/__init__.py
recipe/on_error.py
recipe/recipe_core.py
recipe/tools.py
recipe/types_.py
recipe/util.py
python_recipe-0.1.dist-info/LICENSE
python_recipe-0.1.dist-info/METADATA
python_recipe-0.1.dist-info/WHEEL
python_recipe-0.1.dist-info/top_level.txt
python_recipe-0.1.dist-info/RECORD
