Metadata-Version: 2.1
Name: python-recipe
Version: 0.1
Summary: Let's cook some values!
Author-email: Yann Tremblay <yanntremblay@tombmyst.ca>
License: This is free and unencumbered software released into the public domain.        
Project-URL: Homepage, https://github.com/Tombmyst/python-recipe
Project-URL: Bug Tracker, https://github.com/Tombmyst/python-recipe/issues
Classifier: Development Status :: 5 - Production/Stable
Classifier: Intended Audience :: Developers
Classifier: License :: OSI Approved :: The Unlicense (Unlicense)
Classifier: Operating System :: OS Independent
Classifier: Programming Language :: Python :: 3 :: Only
Classifier: Programming Language :: Python :: 3.10
Classifier: Topic :: Software Development :: Libraries :: Python Modules
Classifier: Topic :: Utilities
Classifier: Typing :: Typed
Requires-Python: >=3.10
License-File: LICENSE
Provides-Extra: tests
Requires-Dist: pytest (==7.1.2) ; extra == 'tests'
Requires-Dist: pytest-cov (==3.0.0) ; extra == 'tests'
Requires-Dist: black (==22.6.0) ; extra == 'tests'
Requires-Dist: pylint (==2.14.5) ; extra == 'tests'
Requires-Dist: docformatter (==1.4) ; extra == 'tests'
